ditolo/__init__.py
ditolo/__main__.py
ditolo-0.1.6.dist-info/LICENSE
ditolo-0.1.6.dist-info/METADATA
ditolo-0.1.6.dist-info/WHEEL
ditolo-0.1.6.dist-info/top_level.txt
ditolo-0.1.6.dist-info/RECORD
