Metadata-Version: 2.1
Name: ditolo
Version: 0.1.6
Summary: discord extension package ditolo
Home-page: https://github.com/zearakun/discord-token-login-packege
Author: Za
License: MIT
Platform: UNKNOWN
